spendee/__init__.py
spendee/exceptions.py
spendee/spendee.py
spendee-1.0.dist-info/LICENSE
spendee-1.0.dist-info/METADATA
spendee-1.0.dist-info/WHEEL
spendee-1.0.dist-info/top_level.txt
spendee-1.0.dist-info/RECORD
