Metadata-Version: 2.1
Name: spendee
Version: 1.0
Summary: Wrapper for the Spendee API
Home-page: https://github.com/dionysio/spendee
Author: Dionyz Lazar
Author-email: dio@dionysio.com
License: UNKNOWN
Download-URL: https://github.com/dionysio/spendee/archive/v0.1.0.tar.gz
Platform: UNKNOWN
Classifier: Programming Language :: Python :: 3
Classifier: License :: OSI Approved :: MIT License
Classifier: Operating System :: OS Independent
Requires-Python: >=3.7
Requires-Dist: requests
